foru_ms_sdk/__init__.py
foru_ms_sdk/auth/__init__.py
foru_ms_sdk/auth/client.py
foru_ms_sdk/auth/raw_client.py
foru_ms_sdk/client.py
foru_ms_sdk/core/__init__.py
foru_ms_sdk/core/api_error.py
foru_ms_sdk/core/client_wrapper.py
foru_ms_sdk/core/datetime_utils.py
foru_ms_sdk/core/file.py
foru_ms_sdk/core/force_multipart.py
foru_ms_sdk/core/http_client.py
foru_ms_sdk/core/http_response.py
foru_ms_sdk/core/http_sse/__init__.py
foru_ms_sdk/core/http_sse/_api.py
foru_ms_sdk/core/http_sse/_decoders.py
foru_ms_sdk/core/http_sse/_exceptions.py
foru_ms_sdk/core/http_sse/_models.py
foru_ms_sdk/core/jsonable_encoder.py
foru_ms_sdk/core/pydantic_utilities.py
foru_ms_sdk/core/query_encoder.py
foru_ms_sdk/core/remove_none_from_dict.py
foru_ms_sdk/core/request_options.py
foru_ms_sdk/core/serialization.py
foru_ms_sdk/environment.py
foru_ms_sdk/errors/__init__.py
foru_ms_sdk/errors/bad_request_error.py
foru_ms_sdk/errors/conflict_error.py
foru_ms_sdk/errors/forbidden_error.py
foru_ms_sdk/errors/internal_server_error.py
foru_ms_sdk/errors/not_found_error.py
foru_ms_sdk/errors/payment_required_error.py
foru_ms_sdk/errors/too_many_requests_error.py
foru_ms_sdk/errors/unauthorized_error.py
foru_ms_sdk/integrations/__init__.py
foru_ms_sdk/integrations/client.py
foru_ms_sdk/integrations/raw_client.py
foru_ms_sdk/integrations/types/__init__.py
foru_ms_sdk/integrations/types/update_integrations_response.py
foru_ms_sdk/integrations/types/update_integrations_response_data.py
foru_ms_sdk/integrations/types/update_integrations_response_data_type.py
foru_ms_sdk/notifications/__init__.py
foru_ms_sdk/notifications/client.py
foru_ms_sdk/notifications/raw_client.py
foru_ms_sdk/notifications/types/__init__.py
foru_ms_sdk/notifications/types/create_notifications_request_status.py
foru_ms_sdk/notifications/types/list_notifications_request_status.py
foru_ms_sdk/notifications/types/update_notifications_request_status.py
foru_ms_sdk/notifications/types/update_notifications_response.py
foru_ms_sdk-0.0.24.dist-info/METADATA
foru_ms_sdk-0.0.24.dist-info/WHEEL
foru_ms_sdk-0.0.24.dist-info/RECORD
